{
  "UFU6S8": {
    "claimed_by": null,
    "claimed_at": null,
    "shortener": "linkcents"
  },
  "ZZPSUL": {
    "claimed_by": null,
    "claimed_at": null,
    "shortener": "linkcents"
  },
  "BPS057": {
    "claimed_by": null,
    "claimed_at": null,
    "shortener": "linkcents"
  },
  "SFCUA9": {
    "claimed_by": null,
    "claimed_at": null,
    "shortener": "linkcents"
  },
  "OYP628": {
    "claimed_by": null,
    "claimed_at": null,
    "shortener": "linkcents"
  },
  "GXHY5I": {
    "claimed_by": null,
    "claimed_at": null,
    "shortener": "linkcents"
  }
}